gtfslite/__init__.py
gtfslite/exceptions.py
gtfslite/gtfs.py
gtfs_lite-0.2.1.dist-info/LICENSE
gtfs_lite-0.2.1.dist-info/METADATA
gtfs_lite-0.2.1.dist-info/WHEEL
gtfs_lite-0.2.1.dist-info/top_level.txt
gtfs_lite-0.2.1.dist-info/RECORD
