Metadata-Version: 2.1
Name: gtfs-lite
Version: 0.2.1
Summary: A lightweight Pandas-driven package for analyzing static GTFS feeds.
Home-page: https://github.com/wklumpen/gtfs-lite
Author: Willem Klumpenhouwer
Author-email: willem@klumpentown.com
Classifier: Programming Language :: Python :: 3
Classifier: License :: OSI Approved :: MIT License
Classifier: Operating System :: OS Independent
Classifier: Development Status :: 4 - Beta
Classifier: Intended Audience :: Science/Research
Classifier: Natural Language :: English
Requires-Python: >=3.6
License-File: LICENSE
Requires-Dist: pandas >=1.5
